{
  "goblin": {
    "name": "Goblin Lv.1",
    "level": 1,
    "min_player_level": 1,
    "base_stats": {
      "dexterity": 10,
      "constitution": 7,
      "strength": 8
    },
    "skills": [
      "quick_strike",
      "basic_attack",
      "web_shot"
    ],
    "behavior": "smart",
    "skill_sequence": [
      "web_shot",
      "quick_strike",
      "basic_attack",
      "web_shot",
      "quick_strike",
      "basic_attack"
    ]
  },
  "goblin_archer": {
    "name": "Goblin Archer Lv.2",
    "level": 2,
    "min_player_level": 2,
    "base_stats": {
      "dexterity": 12,
      "constitution": 8,
      "strength": 9
    },
    "skills": [
      "quick_strike",
      "poison_dart",
      "web_shot"
    ],
    "behavior": "smart",
    "skill_sequence": [
      "web_shot",
      "poison_dart",
      "quick_strike",
      "web_shot",
      "poison_dart",
      "quick_strike"
    ]
  },
  "orc": {
    "name": "Orc Lv.1",
    "level": 1,
    "min_player_level": 1,
    "base_stats": {
      "strength": 11,
      "constitution": 10,
      "dexterity": 6
    },
    "damage": 4,
    "skills": [
      "battle_cry",
      "basic_attack",
      "power_attack"
    ],
    "behavior": "smart",
    "skill_sequence": [
      "battle_cry",
      "power_attack",
      "basic_attack",
      "power_attack",
      "basic_attack",
      "battle_cry"
    ]
  },
  "orc_warrior": {
    "name": "Orc Warrior Lv.3",
    "level": 3,
    "min_player_level": 3,
    "base_stats": {
      "strength": 13,
      "constitution": 12,
      "dexterity": 7
    },
    "damage": 5,
    "defense": 2,
    "skills": [
      "battle_cry",
      "shield_bash",
      "power_attack"
    ],
    "behavior": "smart",
    "skill_sequence": [
      "battle_cry",
      "shield_bash",
      "power_attack",
      "shield_bash",
      "power_attack",
      "battle_cry"
    ]
  },
  "skeleton": {
    "name": "Skeleton Lv.1",
    "level": 1,
    "min_player_level": 1,
    "base_stats": {
      "constitution": 5,
      "intelligence": 8,
      "wisdom": 8,
      "dexterity": 9
    },
    "defense": 2,
    "skills": [
      "poison_dart",
      "bone_spear",
      "basic_attack"
    ],
    "behavior": "smart",
    "skill_sequence": [
      "poison_dart",
      "bone_spear",
      "basic_attack",
      "bone_spear",
      "poison_dart",
      "basic_attack"
    ]
  },
  "skeleton_mage": {
    "name": "Skeleton Mage Lv.4",
    "level": 4,
    "min_player_level": 4,
    "base_stats": {
      "constitution": 6,
      "intelligence": 12,
      "wisdom": 10,
      "dexterity": 8
    },
    "defense": 1,
    "skills": [
      "bone_spear",
      "poison_dart",
      "ice_spike"
    ],
    "behavior": "smart",
    "skill_sequence": [
      "poison_dart",
      "ice_spike",
      "bone_spear",
      "ice_spike",
      "bone_spear",
      "poison_dart"
    ]
  },
  "troll": {
    "name": "Troll Lv.5",
    "level": 5,
    "min_player_level": 5,
    "base_stats": {
      "strength": 14,
      "constitution": 14,
      "dexterity": 5,
      "intelligence": 4,
      "wisdom": 4
    },
    "damage": 6,
    "defense": 3,
    "skills": [
      "regenerate",
      "power_attack",
      "shield_bash"
    ],
    "behavior": "smart",
    "skill_sequence": [
      "regenerate",
      "shield_bash",
      "power_attack",
      "shield_bash",
      "power_attack",
      "regenerate"
    ]
  },
  "troll_berserker": {
    "name": "Troll Berserker Lv.7",
    "level": 7,
    "min_player_level": 7,
    "base_stats": {
      "strength": 16,
      "constitution": 15,
      "dexterity": 6,
      "intelligence": 4,
      "wisdom": 4
    },
    "damage": 8,
    "defense": 2,
    "skills": [
      "battle_cry",
      "regenerate",
      "power_attack"
    ],
    "behavior": "smart",
    "skill_sequence": [
      "battle_cry",
      "regenerate",
      "power_attack",
      "power_attack",
      "power_attack",
      "regenerate"
    ]
  },
  "dark_elf": {
    "name": "Dark Elf Lv.6",
    "level": 6,
    "min_player_level": 6,
    "base_stats": {
      "strength": 8,
      "dexterity": 14,
      "constitution": 7,
      "intelligence": 12,
      "wisdom": 10
    },
    "skills": [
      "shadow_step",
      "poison_dart",
      "quick_strike"
    ],
    "behavior": "smart",
    "skill_sequence": [
      "shadow_step",
      "poison_dart",
      "quick_strike",
      "quick_strike",
      "poison_dart",
      "shadow_step"
    ]
  },
  "dark_elf_assassin": {
    "name": "Dark Elf Assassin Lv.8",
    "level": 8,
    "min_player_level": 8,
    "base_stats": {
      "strength": 10,
      "dexterity": 16,
      "constitution": 8,
      "intelligence": 14,
      "wisdom": 12
    },
    "skills": [
      "shadow_step",
      "poison_dart",
      "vampiric_strike"
    ],
    "behavior": "smart",
    "skill_sequence": [
      "shadow_step",
      "vampiric_strike",
      "poison_dart",
      "vampiric_strike",
      "shadow_step",
      "poison_dart"
    ]
  },
  "dragon_whelp": {
    "name": "Dragon Whelp Lv.10",
    "level": 10,
    "min_player_level": 10,
    "base_stats": {
      "strength": 14,
      "dexterity": 12,
      "constitution": 16,
      "intelligence": 14,
      "wisdom": 14
    },
    "damage": 10,
    "defense": 5,
    "skills": [
      "flame_breath",
      "regenerate",
      "power_attack",
      "battle_cry"
    ],
    "behavior": "smart",
    "skill_sequence": [
      "battle_cry",
      "flame_breath",
      "power_attack",
      "regenerate",
      "flame_breath",
      "power_attack",
      "battle_cry",
      "regenerate"
    ]
  }
}